[
  {
    "id": "song2026-rascene-mmwave-communication-3d-imaging",
    "title": "Rascene: High-Fidelity 3D Scene Imaging with mmWave Communication Signals",
    "authors": "Kunzhe Song; Geo Jie Zhou; Xiaoming Liu; Huacheng Zeng",
    "year": 2026,
    "publication_date": "2026-04-03",
    "venue": "arXiv preprint",
    "venue_group": "arXiv",
    "venue_type": "preprint",
    "doi": "",
    "primary_url": "https://arxiv.org/abs/2604.02603",
    "pdf_url": "https://arxiv.org/pdf/2604.02603",
    "project_url": "",
    "code_url": "",
    "topics": ["mmWave radar imaging", "ISAC", "3D scene reconstruction", "multi-frame fusion", "communication signals"],
    "relevance": "core",
    "summary_cn": "利用毫米波 OFDM 通信信号进行三维场景成像，通过多帧空间自适应融合恢复几何一致性。",
    "why_include_cn": "代表毫米波通信信号与三维成像结合的最新 ISAC 方向，关注低成本、可扩展的三维环境感知。",
    "download_note": "No final venue was verified at the time of curation; arXiv is recorded as the preprint source.",
    "sources": ["https://arxiv.org/abs/2604.02603"],
    "last_verified": "2026-06-26",
    "curation_origin": "mmwave-track-public"
  },
  {
    "id": "micorosa2026-ris-aided-mmwave-3d-imaging",
    "title": "RIS-Aided Sensing: Experimental Validation of Radar 3D Imaging in the mmWave Band",
    "authors": "Sergio Micó-Rosa; Alvaro Villaescusa-Tebar; Saúl Fenollosa; Carlos Villena-Jiménez; Monika Drozdowska; Narcis Cardona",
    "year": 2026,
    "publication_date": "2026-04-14",
    "venue": "arXiv preprint",
    "venue_group": "arXiv",
    "venue_type": "preprint",
    "doi": "",
    "primary_url": "https://arxiv.org/abs/2604.12466",
    "pdf_url": "https://arxiv.org/pdf/2604.12466",
    "project_url": "",
    "code_url": "",
    "topics": ["mmWave radar imaging", "RIS-aided sensing", "FMCW radar", "3D voxel reconstruction", "ISAC"],
    "relevance": "related",
    "summary_cn": "将 FMCW 雷达、1-bit RIS 与 SFCW 测量结合，用于毫米波频段三维目标/场景重建验证。",
    "why_include_cn": "展示可重构智能表面辅助毫米波三维成像的实验框架，适合作为新型硬件调制和三维重建参考。",
    "download_note": "No final venue was verified at the time of curation; arXiv is recorded as the preprint source.",
    "sources": ["https://arxiv.org/abs/2604.12466"],
    "last_verified": "2026-06-26",
    "curation_origin": "mmwave-track-public"
  },
  {
    "id": "jha2025-mimo-sar-fmcw-radar-3d-image-reconstruction",
    "title": "3D-Image Reconstruction using MIMO-SAR FMCW Radar",
    "authors": "Ayush Jha; Dhanireddy Chandrika; Chandra Sekhar Seelamantula; Chetan Singh Thakur",
    "year": 2025,
    "publication_date": "2025-09-07",
    "venue": "arXiv preprint",
    "venue_group": "arXiv",
    "venue_type": "preprint",
    "doi": "",
    "primary_url": "https://arxiv.org/abs/2509.05977",
    "pdf_url": "https://arxiv.org/pdf/2509.05977",
    "project_url": "",
    "code_url": "",
    "topics": ["mmWave radar imaging", "MIMO-SAR", "FMCW radar", "3D reconstruction", "time-domain reconstruction"],
    "relevance": "core",
    "summary_cn": "结合 MIMO FMCW 虚拟阵列与合成孔径扫描，进行毫米波三维雷达图像重建。",
    "why_include_cn": "直接覆盖 MIMO-SAR、FMCW 和三维毫米波成像，是雷达三维成像算法方向的高相关工作。",
    "download_note": "No final venue was verified at the time of curation; arXiv is recorded as the preprint source.",
    "sources": ["https://arxiv.org/abs/2509.05977"],
    "last_verified": "2026-06-26",
    "curation_origin": "mmwave-track-public"
  },
  {
    "id": "hussein2025-rfconstruct-3d-object-reconstruction-mmwave",
    "title": "3D Object Reconstruction with mmWave Radars",
    "authors": "Samah Hussein; Junfeng Guan; Swathi Narashiman; Saurabh Gupta; Haitham Hassanieh",
    "year": 2025,
    "publication_date": "2025-04-15",
    "venue": "arXiv preprint",
    "venue_group": "arXiv",
    "venue_type": "preprint",
    "doi": "",
    "primary_url": "https://arxiv.org/abs/2504.12348",
    "pdf_url": "https://arxiv.org/pdf/2504.12348",
    "project_url": "",
    "code_url": "",
    "topics": ["mmWave radar imaging", "3D object reconstruction", "multi-radar fusion", "temporal fusion", "point cloud completion"],
    "relevance": "core",
    "summary_cn": "RFconstruct 使用商用毫米波雷达进行三维物体形状重建，结合多雷达正交视角、时序融合和学习式补全。",
    "why_include_cn": "面向稀疏、低角分辨和镜面反射等毫米波雷达挑战，提供系统级三维形状重建方案。",
    "download_note": "No final venue was verified at the time of curation; arXiv is recorded as the preprint source.",
    "sources": ["https://arxiv.org/abs/2504.12348"],
    "last_verified": "2026-06-26",
    "curation_origin": "mmwave-track-public"
  },
  {
    "id": "wu2025-diffusion-range-image-mmwave-point-cloud",
    "title": "Diffusion-Based mmWave Radar Point Cloud Enhancement Driven by Range Images",
    "authors": "Ruixin Wu; Zihan Li; Jin Wang; Xiangyu Xu; Zhi Zheng; Kaixiang Huang; Guodong Lu",
    "year": 2025,
    "publication_date": "2025-03-04",
    "venue": "arXiv preprint",
    "venue_group": "arXiv",
    "venue_type": "preprint",
    "doi": "",
    "primary_url": "https://arxiv.org/abs/2503.02300",
    "pdf_url": "https://arxiv.org/pdf/2503.02300",
    "project_url": "",
    "code_url": "",
    "topics": ["mmWave radar point cloud", "diffusion model", "range image", "point cloud enhancement", "3D reconstruction"],
    "relevance": "related",
    "summary_cn": "用 range image 表示连接毫米波雷达点云增强与图像扩散模型，生成更稠密的类 LiDAR 三维点云。",
    "why_include_cn": "关注毫米波点云稀疏和噪声问题，适合作为学习式点云增强和跨表示建模参考。",
    "download_note": "No final venue was verified at the time of curation; arXiv is recorded as the preprint source.",
    "sources": ["https://arxiv.org/abs/2503.02300"],
    "last_verified": "2026-06-26",
    "curation_origin": "mmwave-track-public"
  },
  {
    "id": "fan2024-mmemp-visual-inertial-supervision-mmwave-point-cloud",
    "title": "Enhancing mmWave Radar Point Cloud via Visual-inertial Supervision",
    "authors": "Cong Fan; Shengkai Zhang; Kezhong Liu; Shuai Wang; Zheng Yang; Wei Wang",
    "year": 2024,
    "publication_date": "2024-04-26",
    "venue": "arXiv preprint",
    "venue_group": "arXiv",
    "venue_type": "preprint",
    "doi": "",
    "primary_url": "https://arxiv.org/abs/2404.17229",
    "pdf_url": "https://arxiv.org/pdf/2404.17229",
    "project_url": "",
    "code_url": "",
    "topics": ["mmWave radar point cloud", "visual-inertial supervision", "point cloud enhancement", "multipath suppression", "3D reconstruction"],
    "relevance": "related",
    "summary_cn": "mmEMP 用低成本相机与 IMU 监督毫米波雷达点云增强，处理动态对象和多径伪点问题。",
    "why_include_cn": "代表视觉/惯性监督与毫米波雷达点云增强结合的方向，对低成本监督和多径抑制有参考价值。",
    "download_note": "No final venue was verified at the time of curation; arXiv is recorded as the preprint source.",
    "sources": ["https://arxiv.org/abs/2404.17229"],
    "last_verified": "2026-06-26",
    "curation_origin": "mmwave-track-public"
  },
  {
    "id": "sun2021-3drimr-mmwave-radar-reconstruction",
    "title": "3DRIMR: 3D Reconstruction and Imaging via mmWave Radar based on Deep Learning",
    "authors": "Yue Sun; Zhuoming Huang; Honggang Zhang; Zhi Cao; Deqiang Xu",
    "year": 2021,
    "publication_date": "2021-08-05",
    "venue": "arXiv preprint",
    "venue_group": "arXiv",
    "venue_type": "preprint",
    "doi": "",
    "primary_url": "https://arxiv.org/abs/2108.02858",
    "pdf_url": "https://arxiv.org/pdf/2108.02858",
    "project_url": "",
    "code_url": "",
    "topics": ["mmWave radar imaging", "3D reconstruction", "deep learning", "point cloud reconstruction", "radar intensity"],
    "relevance": "core",
    "summary_cn": "3DRIMR 将毫米波雷达强度数据映射到深度图和三维点云，是学习式毫米波三维成像的早期代表。",
    "why_include_cn": "作为毫米波雷达三维重建的基础工作，覆盖稀疏、低分辨、镜面反射和多径伪影等关键挑战。",
    "download_note": "No final venue was verified at the time of curation; arXiv is recorded as the preprint source.",
    "sources": ["https://arxiv.org/abs/2108.02858"],
    "last_verified": "2026-06-26",
    "curation_origin": "mmwave-track-public"
  }
]
